textconv/__init__.py
textconv/text.py
textconv/tests/__init__.py
textconv/tests/test_textconv.py
textconv-0.0.1.dist-info/LICENSE
textconv-0.0.1.dist-info/METADATA
textconv-0.0.1.dist-info/WHEEL
textconv-0.0.1.dist-info/top_level.txt
textconv-0.0.1.dist-info/RECORD
