Metadata-Version: 2.1
Name: textconv
Version: 0.0.1
Summary: Convert a string to bytes type or str type
Home-page: https://github.com/sanbaispeaking/textconv
Author: sanbaispeaking
Author-email: sanbaispeaking@outlook.com
License: UNKNOWN
Platform: UNKNOWN
Classifier: Intended Audience :: Information Technology
Classifier: License :: OSI Approved :: MIT License
Classifier: Operating System :: OS Independent
Classifier: Programming Language :: Python :: 3
Classifier: Programming Language :: Python :: 3.5
Classifier: Programming Language :: Python :: 3.6
Requires-Python: >=3.0
